ipop_components/__init__.py
ipop_components/bundle.js
ipop_components/metadata.json
ipop_components/version.py
ipop_components-0.0.2.dist-info/DESCRIPTION.rst
ipop_components-0.0.2.dist-info/METADATA
ipop_components-0.0.2.dist-info/RECORD
ipop_components-0.0.2.dist-info/WHEEL
ipop_components-0.0.2.dist-info/metadata.json
ipop_components-0.0.2.dist-info/top_level.txt
