Metadata-Version: 2.0
Name: ipop-components
Version: 0.0.2
Summary: IPOP Portal Components Suite
Home-page: UNKNOWN
Author: rmarren1
Author-email: UNKNOWN
License: MIT
Platform: UNKNOWN
